print_wcolor/__init__.py
print_wcolor/print_wcolor.py
print_wcolor-0.0.8.dist-info/LICENSE
print_wcolor-0.0.8.dist-info/METADATA
print_wcolor-0.0.8.dist-info/WHEEL
print_wcolor-0.0.8.dist-info/top_level.txt
print_wcolor-0.0.8.dist-info/RECORD
