Metadata-Version: 2.1
Name: print-wcolor
Version: 0.0.8
Summary: print_wcolor
Home-page: https://github.com/wanggaoping/print_wcolor.git
Author: wgp
Author-email: 819032030@qq.com
License: UNKNOWN
Platform: UNKNOWN
Classifier: Programming Language :: Python :: 3
Classifier: License :: OSI Approved :: MIT License
Classifier: Operating System :: OS Independent
License-File: LICENSE
